setup.cfg
setup.py
jinja2_commentif/__init__.py
jinja2_commentif/ext.py
jinja2_commentif.egg-info/PKG-INFO
jinja2_commentif.egg-info/SOURCES.txt
jinja2_commentif.egg-info/dependency_links.txt
jinja2_commentif.egg-info/requires.txt
jinja2_commentif.egg-info/top_level.txt
tests/__init__.py
tests/test_commentif.py