Metadata-Version: 1.0
Name: jinja2-commentif
Version: 0.2
Summary: Jinja2 extension to automatically add a comment prefix on each line
Home-page: https://github.com/zehome/jinja2-commentif
Author: Laurent COUSTET
Author-email: ed@zehome.com
License: = BSD2
Platform: UNKNOWN
